AUTHORS.rst
CONTRIBUTING.rst
HISTORY.rst
LICENSE
MANIFEST.in
README.rst
setup.py
django_sieve.egg-info/PKG-INFO
django_sieve.egg-info/SOURCES.txt
django_sieve.egg-info/dependency_links.txt
django_sieve.egg-info/not-zip-safe
django_sieve.egg-info/top_level.txt
sieve/__init__.py
sieve/models.py
sieve/.ropeproject/config.py
sieve/static/js/sieve.js
sieve/templates/sieve/base.html
sieve/testproject/manage.py
sieve/testproject/bookstore/__init__.py
sieve/testproject/bookstore/admin.py
sieve/testproject/bookstore/models.py
sieve/testproject/bookstore/tests.py
sieve/testproject/bookstore/urls.py
sieve/testproject/bookstore/views.py
sieve/testproject/bookstore/.ropeproject/config.py
sieve/testproject/testproject/__init__.py
sieve/testproject/testproject/settings.py
sieve/testproject/testproject/urls.py
sieve/testproject/testproject/wsgi.py
sieve/testproject/testproject/.ropeproject/config.py
sieve/testproject/testproject/templates/base.html
sieve/testproject/testproject/templates/bookstore/author_list.html
sieve/testproject/testproject/templates/bookstore/book_list.html
sieve/testproject/testproject/templates/bookstore/publisher_list.html