Metadata-Version: 1.1
Name: django-sieve
Version: 1.0.0
Summary: Filter user-data based on multiple criteria.
Home-page: https://github.com/alixedi/django_sieve
Author: Ali Zaidi
Author-email: alixedi@gmail.com
License: BSD
Keywords: django_sieve
Platform: UNKNOWN
Classifier: Development Status :: 2 - Pre-Alpha
Classifier: Framework :: Django
Classifier: Intended Audience :: Developers
Classifier: License :: OSI Approved :: BSD License
Classifier: Natural Language :: English
Classifier: Programming Language :: Python :: 2
Classifier: Programming Language :: Python :: 2.6
Classifier: Programming Language :: Python :: 2.7
Classifier: Programming Language :: Python :: 3
Classifier: Programming Language :: Python :: 3.3
